gauge_web_app_steps/__init__.py
gauge_web_app_steps/app_context.py
gauge_web_app_steps/bymapper.py
gauge_web_app_steps/element_lookup.py
gauge_web_app_steps/imagepaths.py
gauge_web_app_steps/images.py
gauge_web_app_steps/keymapper.py
gauge_web_app_steps/report.py
gauge_web_app_steps/sauce_tunnel.py
gauge_web_app_steps/screenshot.py
gauge_web_app_steps/selector.py
gauge_web_app_steps/substitute.py
gauge_web_app_steps/web_app_steps.py
gauge_web_app_steps/config/__init__.py
gauge_web_app_steps/config/common_config.py
gauge_web_app_steps/config/local_config.py
gauge_web_app_steps/config/saucelabs_config.py
gauge_web_app_steps/driver/__init__.py
gauge_web_app_steps/driver/browsers.py
gauge_web_app_steps/driver/driver_factory.py
gauge_web_app_steps/driver/operating_system.py
gauge_web_app_steps/driver/platform.py
gauge_web_app_steps-0.66.dist-info/licenses/LICENCE
gauge_web_app_steps-0.66.dist-info/METADATA
gauge_web_app_steps-0.66.dist-info/WHEEL
gauge_web_app_steps-0.66.dist-info/top_level.txt
gauge_web_app_steps-0.66.dist-info/RECORD
