Metadata-Version: 2.4
Name: gauge-web-app-steps
Version: 0.66
Summary: Provides basic steps for a Gauge project, that runs tests with Selenium and Appium
Home-page: https://github.com/IBM/gauge-web-app-steps
Author: Tobias Lehmann
Author-email: derdualist1@gmail.com
License: MIT
License-File: LICENCE
Requires-Dist: Appium-Python-Client==4.5.1
Requires-Dist: getgauge>=0.4.8
Requires-Dist: numexpr==2.10.2
Requires-Dist: numpy==2.2.4
Requires-Dist: scikit-image==0.25.2
Requires-Dist: selenium==4.30.0
Requires-Dist: webcolors==24.11.1
Requires-Dist: webdriver-manager==4.0.2
Dynamic: author
Dynamic: author-email
Dynamic: description
Dynamic: description-content-type
Dynamic: home-page
Dynamic: license
Dynamic: license-file
Dynamic: requires-dist
Dynamic: summary
